15_Shift_Register/shift_register.v
module shift_register (
    input clk,
    input serial_in,
    output reg [3:0] q
);

always @(posedge clk)
begin
    q <= {q[2:0], serial_in};
end

endmodule

15_Shift_Register/shift_register_tb.v
`timescale 1ns/1ps

module shift_register_tb;

reg clk;
reg serial_in;

wire [3:0] q;

// Instantiate Shift Register

shift_register uut (
    .clk(clk),
    .serial_in(serial_in),
    .q(q)
);

// Clock generation

initial begin
    clk = 0;
    forever #5 clk = ~clk;
end

// Test sequence

initial begin

    $dumpfile("shift_register.vcd");
    $dumpvars(0, shift_register_tb);

    serial_in = 1;
    #20;

    serial_in = 0;
    #20;

    serial_in = 1;
    #20;

    serial_in = 0;
    #20;

    $finish;

end

endmodule

15_Shift_Register/shift_register.vcd
$date
	Sun Jul 19 23:40:58 2026
$end
$version
	Icarus Verilog
$end
$timescale
	1ps
$end
$scope module shift_register_tb $end
$var wire 4 ! q [3:0] $end
$var reg 1 " clk $end
$var reg 1 # serial_in $end
$scope module uut $end
$var wire 1 " clk $end
$var wire 1 # serial_in $end
$var reg 4 $ q [3:0] $end
$upscope $end
$upscope $end
$enddefinitions $end
#0
$dumpvars
bx $
1#
0"
bx !
$end
#5000
bx1 !
bx1 $
1"
#10000
0"
#15000
bx11 !
bx11 $
1"
#20000
0"
0#
#25000
bx110 !
bx110 $
1"
#30000
0"
#35000
b1100 !
b1100 $
1"
#40000
0"
1#
#45000
b1001 !
b1001 $
1"
#50000
0"
#55000
b11 !
b11 $
1"
#60000
0"
0#
#65000
b110 !
b110 $
1"
#70000
0"
#75000
b1100 !
b1100 $
1"
