18_Moore_FSM/moore_fsm.v
module moore_fsm (
    input clk,
    input x,
    output reg y
);

reg [1:0] state;

parameter S0 = 2'b00,
          S1 = 2'b01,
          S2 = 2'b10,
          S3 = 2'b11;

initial begin
    state = S0;
    y = 0;
end

always @(posedge clk)
begin
    case(state)

        S0:
        begin
            y <= 0;
            if(x)
                state <= S1;
        end

        S1:
        begin
            y <= 0;
            if(x)
                state <= S1;
            else
                state <= S2;
        end

        S2:
        begin
            y <= 0;
            if(x)
                state <= S3;
            else
                state <= S0;
        end

        S3:
        begin
            y <= 1;
            state <= S0;
        end

    endcase
end

endmodule

18_Moore_FSM/moore_fsm_tb.v
`timescale 1ns/1ps

module moore_fsm_tb;

reg clk;
reg x;

wire y;

moore_fsm uut(
    .clk(clk),
    .x(x),
    .y(y)
);

// Clock generation

initial begin
    clk = 0;
    forever #5 clk = ~clk;
end

initial begin

    $dumpfile("moore_fsm.vcd");
    $dumpvars(0, moore_fsm_tb);

    // Sequence: 1 0 1
    x = 1; #10;
    x = 0; #10;
    x = 1; #10;

    // Random inputs
    x = 0; #10;
    x = 1; #10;
    x = 1; #10;

    $finish;

end

endmodule

18_Moore_FSM/moore_fsm.vcd
$date
	Mon Jul 20 10:10:09 2026
$end
$version
	Icarus Verilog
$end
$timescale
	1ps
$end
$scope module moore_fsm_tb $end
$var wire 1 ! y $end
$var reg 1 " clk $end
$var reg 1 # x $end
$scope module uut $end
$var wire 1 " clk $end
$var wire 1 # x $end
$var reg 2 $ state [1:0] $end
$var reg 1 ! y $end
$upscope $end
$upscope $end
$enddefinitions $end
#0
$dumpvars
b0 $
1#
0"
0!
$end
#5000
b1 $
1"
#10000
0"
0#
#15000
b10 $
1"
#20000
0"
1#
#25000
b11 $
1"
#30000
0"
0#
#35000
b0 $
1!
1"
#40000
0"
1#
#45000
b1 $
0!
1"
