17_Debouncer/Debouncer.v
module debouncer (
    input clk,
    input button,
    output reg button_out
);

reg [2:0] counter = 0;

always @(posedge clk)
begin
    if(button == button_out)
    begin
        counter <= 0;
    end
    else
    begin
        counter <= counter + 1;

        if(counter == 3'b111)
        begin
            button_out <= button;
            counter <= 0;
        end
    end
end

endmodule

17_Debouncer/Debouncer_tb.v
`timescale 1ns/1ps

module debouncer_tb;

reg clk;
reg button;

wire button_out;

debouncer uut(
    .clk(clk),
    .button(button),
    .button_out(button_out)
);

// Clock

initial begin
    clk = 0;
    forever #5 clk = ~clk;
end

// Button bounce simulation

initial begin

    $dumpfile("debouncer.vcd");
    $dumpvars(0, debouncer_tb);

    button = 0;

    #20;

    // Simulated bouncing
    button = 1; #5;
    button = 0; #5;
    button = 1; #5;
    button = 0; #5;
    button = 1;

    #100;

    $finish;

end

endmodule

17_Debouncer/debouncer.vcd
$date
	Mon Jul 20 09:59:35 2026
$end
$version
	Icarus Verilog
$end
$timescale
	1ps
$end
$scope module debouncer_tb $end
$var wire 1 ! button_out $end
$var reg 1 " button $end
$var reg 1 # clk $end
$scope module uut $end
$var wire 1 " button $end
$var wire 1 # clk $end
$var reg 1 ! button_out $end
$var reg 3 $ counter [2:0] $end
$upscope $end
$upscope $end
$enddefinitions $end
#0
$dumpvars
b0 $
0#
0"
x!
$end
#5000
b1 $
1#
#10000
0#
#15000
b10 $
1#
#20000
0#
1"
#25000
b11 $
1#
0"
#30000
0#
1"
#35000
b100 $
1#
0"
#40000
0#
1"
#45000
b101 $
1#
#50000
0#
#55000
b110 $
1#
#60000
0#
#65000
b111 $
1#
#70000
0#
#75000
1!
b0 $
1#
