12_D_FlipFlop/d_flipflop.v
module d_flipflop (
    input clk,
    input d,
    output reg q
);

always @(posedge clk)
begin
    q <= d;
end

endmodule

12_D_FlipFlop/d_flipflop_tb.v
`timescale 1ns/1ps

module d_flipflop_tb;

reg clk;
reg d;

wire q;

// Instantiate D Flip-Flop

d_flipflop uut (
    .clk(clk),
    .d(d),
    .q(q)
);

// Clock generation
initial begin
    clk = 0;
    forever #5 clk = ~clk;
end

// Test inputs
initial begin

    $dumpfile("d_flipflop.vcd");
    $dumpvars(0, d_flipflop_tb);

    d = 0;
    #10;

    d = 1;
    #10;

    d = 0;
    #10;

    d = 1;
    #10;

    $finish;

end

endmodule

12_D_FlipFlop/d_flipflop.vcd
$date
	Sun Jul 19 23:04:30 2026
$end
$version
	Icarus Verilog
$end
$timescale
	1ps
$end
$scope module d_flipflop_tb $end
$var wire 1 ! q $end
$var reg 1 " clk $end
$var reg 1 # d $end
$scope module uut $end
$var wire 1 " clk $end
$var wire 1 # d $end
$var reg 1 ! q $end
$upscope $end
$upscope $end
$enddefinitions $end
#0
$dumpvars
0#
0"
x!
$end
#5000
0!
1"
#10000
0"
1#
#15000
1!
1"
#20000
0"
0#
#25000
0!
1"
#30000
0"
1#
#35000
1!
1"
