11_ALU/alu.v
module alu(
    input a,
    input b,
    input [1:0] sel,
    output reg y,
    output reg carry
);

always @(*) begin

    carry = 0;

    case(sel)

        2'b00:
        begin
            y = a & b;
        end

        2'b01:
        begin
            y = a | b;
        end

        2'b10:
        begin
            y = a ^ b;
        end

        2'b11:
        begin
            {carry,y} = a + b;
        end

    endcase

end

endmodule

11_ALU/alu_tb.v
`timescale 1ns/1ps

module alu_tb;

reg a;
reg b;
reg [1:0] sel;

wire y;
wire carry;

// Instantiate ALU

alu uut(
    .a(a),
    .b(b),
    .sel(sel),
    .y(y),
    .carry(carry)
);

initial begin

    $dumpfile("alu.vcd");
    $dumpvars(0, alu_tb);

    // AND
    a=0; b=0; sel=2'b00; #10;
    a=1; b=1; sel=2'b00; #10;

    // OR
    a=0; b=1; sel=2'b01; #10;
    a=1; b=0; sel=2'b01; #10;

    // XOR
    a=0; b=1; sel=2'b10; #10;
    a=1; b=1; sel=2'b10; #10;

    // ADD
    a=0; b=0; sel=2'b11; #10;
    a=0; b=1; sel=2'b11; #10;
    a=1; b=0; sel=2'b11; #10;
    a=1; b=1; sel=2'b11; #10;

    $finish;

end

endmodule

11_ALU/alu.vcd
$date
	Sun Jul 19 22:59:57 2026
$end
$version
	Icarus Verilog
$end
$timescale
	1ps
$end
$scope module alu_tb $end
$var wire 1 ! y $end
$var wire 1 " carry $end
$var reg 1 # a $end
$var reg 1 $ b $end
$var reg 2 % sel [1:0] $end
$scope module uut $end
$var wire 1 # a $end
$var wire 1 $ b $end
$var wire 2 & sel [1:0] $end
$var reg 1 " carry $end
$var reg 1 ! y $end
$upscope $end
$upscope $end
$enddefinitions $end
#0
$dumpvars
b0 &
b0 %
0$
0#
0"
0!
$end
#10000
1!
1$
1#
#20000
b1 %
b1 &
0#
#30000
0$
1#
#40000
b10 %
b10 &
1$
0#
#50000
0!
1#
#60000
b11 %
b11 &
0$
0#
#70000
1!
1$
#80000
0$
1#
#90000
1"
0!
1$
