13_Register/register.v
module register (
    input clk,
    input [3:0] d,
    output reg [3:0] q
);

always @(posedge clk)
begin
    q <= d;
end

endmodule

13_Register/register_tb.v
`timescale 1ns/1ps

module register_tb;

reg clk;
reg [3:0] d;

wire [3:0] q;

// Instantiate Register

register uut (
    .clk(clk),
    .d(d),
    .q(q)
);

// Clock generation
initial begin
    clk = 0;
    forever #5 clk = ~clk;
end

// Test inputs
initial begin

    $dumpfile("register.vcd");
    $dumpvars(0, register_tb);

    d = 4'b0000;
    #10;

    d = 4'b1010;
    #10;

    d = 4'b0101;
    #10;

    d = 4'b1111;
    #10;

    d = 4'b0011;
    #10;

    $finish;

end

endmodule

13_Register/register.vcd
$date
	Sun Jul 19 23:20:33 2026
$end
$version
	Icarus Verilog
$end
$timescale
	1ps
$end
$scope module register_tb $end
$var wire 4 ! q [3:0] $end
$var reg 1 " clk $end
$var reg 4 # d [3:0] $end
$scope module uut $end
$var wire 1 " clk $end
$var wire 4 $ d [3:0] $end
$var reg 4 % q [3:0] $end
$upscope $end
$upscope $end
$enddefinitions $end
#0
$dumpvars
bx %
b0 $
b0 #
0"
bx !
$end
#5000
b0 !
b0 %
1"
#10000
0"
b1010 #
b1010 $
#15000
b1010 !
b1010 %
1"
#20000
0"
b101 #
b101 $
#25000
b101 !
b101 %
1"
#30000
0"
b1111 #
b1111 $
#35000
b1111 !
b1111 %
1"
#40000
0"
b11 #
b11 $
#45000
b11 !
b11 %
1"
